iw/__init__.py
iw/__main__.py
iw-1.0.0.dist-info/METADATA
iw-1.0.0.dist-info/WHEEL
iw-1.0.0.dist-info/top_level.txt
iw-1.0.0.dist-info/RECORD
